qr_code/__init__.py
qr_code/decoder.py
qr_code/encoder.py
tests/__init__.py
tests/test_qr_code.py
qr_code_lib-1.0.0.dist-info/LICENSE
qr_code_lib-1.0.0.dist-info/METADATA
qr_code_lib-1.0.0.dist-info/WHEEL
qr_code_lib-1.0.0.dist-info/top_level.txt
qr_code_lib-1.0.0.dist-info/RECORD
