Metadata-Version: 2.1
Name: qr-code-lib
Version: 1.0.0
Summary: Python project to encode/decode QR Code
Home-page: https://github.com/abhilashsanne/qr_code_lib
Author: Abhilash Sanne
Author-email: sanne.abhi@gmail.com
Classifier: Programming Language :: Python :: 3
Classifier: License :: OSI Approved :: MIT License
Requires-Python: >=3.6
License-File: LICENSE
